<top description='My Description' name='My Data Set'>
  <depth0 name='217' value='0.0' descendants='0.43570288'>
    <depth1 name='173' value='0.08805623' descendants='0.06064227'>
      <depth2 name='173' value='0.00977988' descendants='0.00673517'>
        <depth3 name='173' value='0.00108619' descendants='0.00074804'/>
        <depth3 name='172' value='0.0' descendants='0.00055147'/>
        <depth3 name='174' value='0.0' descendants='4.397e-05'/>
      </depth2>
      <depth2 name='125' value='0.00014495' descendants='0.0001282'/>
      <depth2 name='172' value='0.0' descendants='0.0049653'>
        <depth3 name='173' value='0.00071091' descendants='0.00048959'/>
        <depth3 name='172' value='0.0' descendants='0.00036096'/>
      </depth2>
      <depth2 name='274' value='1.6e-07' descendants='4.726e-05'/>
      <depth2 name='174' value='0.0' descendants='0.00039591'>
        <depth3 name='173' value='0.00028837' descendants='0.00019859'/>
        <depth3 name='172' value='0.0' descendants='0.00014644'/>
        <depth3 name='174' value='0.0' descendants='5.82e-05'/>
      </depth2>
    </depth1>
    <depth1 name='127' value='0.02270427' descendants='0.04664697'>
      <depth2 name='126' value='0.01278904' descendants='0.01376995'>
        <depth3 name='126' value='0.00160968' descendants='0.00173314'/>
        <depth3 name='127' value='0.00017745' descendants='0.00036458'/>
        <depth3 name='125' value='0.00033779' descendants='0.00029876'/>
        <depth3 name='123' value='0.00034864' descendants='0.00011256'/>
        <depth3 name='120' value='3.699e-05' descendants='0.00025275'/>
      </depth2>
      <depth2 name='127' value='0.00154322' descendants='0.00317061'>
        <depth3 name='126' value='0.00086928' descendants='0.00093595'/>
        <depth3 name='127' value='0.00010489' descendants='0.00021551'/>
        <depth3 name='125' value='0.00011229' descendants='9.932e-05'/>
        <depth3 name='120' value='1.504e-05' descendants='0.00010276'/>
      </depth2>
      <depth2 name='125' value='0.00165211' descendants='0.00146121'/>
      <depth2 name='129' value='0.00037482' descendants='0.00026241'/>
      <depth2 name='120' value='0.00022126' descendants='0.00151184'>
        <depth3 name='126' value='0.00045014' descendants='0.00048467'/>
        <depth3 name='127' value='4.47e-05' descendants='9.184e-05'/>
        <depth3 name='120' value='9.93e-06' descendants='6.786e-05'/>
      </depth2>
      <depth2 name='123' value='0.00096413' descendants='0.00031127'/>
      <depth2 name='128' value='5.361e-05' descendants='7.273e-05'/>
      <depth2 name='141' value='6.03e-06' descendants='0.00015327'/>
      <depth2 name='115' value='7.102e-05' descendants='0.0001458'>
        <depth3 name='20' value='0.0' descendants='6.146e-05'/>
      </depth2>
      <depth2 name='149' value='1.08e-06' descendants='5.373e-05'/>
      <depth2 name='121' value='5.61e-06' descendants='5.458e-05'/>
      <depth2 name='44' value='0.0' descendants='7.86e-05'/>
      <depth2 name='78' value='0.0' descendants='4.715e-05'/>
    </depth1>
    <depth1 name='126' value='0.00941494' descendants='0.01013706'>
      <depth2 name='126' value='0.001185' descendants='0.00127589'>
        <depth3 name='126' value='0.00014915' descendants='0.00016059'/>
      </depth2>
      <depth2 name='127' value='0.00013064' descendants='0.0002684'>
        <depth3 name='126' value='7.359e-05' descendants='7.923e-05'/>
      </depth2>
      <depth2 name='125' value='0.00024867' descendants='0.00021994'/>
      <depth2 name='120' value='2.723e-05' descendants='0.00018607'>
        <depth3 name='126' value='5.54e-05' descendants='5.965e-05'/>
      </depth2>
      <depth2 name='123' value='0.00025666' descendants='8.286e-05'/>
    </depth1>
    <depth1 name='120' value='0.00106178' descendants='0.00725495'>
      <depth2 name='126' value='0.00216013' descendants='0.00232581'>
        <depth3 name='126' value='0.00027188' descendants='0.00029274'/>
        <depth3 name='127' value='2.997e-05' descendants='6.158e-05'/>
        <depth3 name='125' value='5.705e-05' descendants='5.046e-05'/>
      </depth2>
      <depth2 name='127' value='0.0002145' descendants='0.00044069'>
        <depth3 name='126' value='0.00012082' descendants='0.00013009'/>
      </depth2>
      <depth2 name='125' value='0.00022316' descendants='0.00019737'/>
      <depth2 name='120' value='4.766e-05' descendants='0.00032562'>
        <depth3 name='126' value='9.695e-05' descendants='0.00010439'/>
      </depth2>
      <depth2 name='123' value='0.00020714' descendants='6.688e-05'/>
      <depth2 name='115' value='2.254e-05' descendants='4.628e-05'/>
      <depth2 name='20' value='0.0' descendants='8.271e-05'/>
    </depth1>
    <depth1 name='202' value='0.00697956' descendants='0.00572106'>
      <depth2 name='173' value='0.00022828' descendants='0.00015721'/>
      <depth2 name='127' value='5.734e-05' descendants='0.0001178'/>
      <depth2 name='202' value='8.859e-05' descendants='7.261e-05'/>
      <depth2 name='172' value='0.0' descendants='0.00011422'/>
      <depth2 name='174' value='0.0' descendants='0.00047763'>
        <depth3 name='173' value='0.00034789' descendants='0.00023959'/>
        <depth3 name='172' value='0.0' descendants='0.00017667'/>
        <depth3 name='174' value='0.0' descendants='7.022e-05'/>
      </depth2>
      <depth2 name='136' value='0.0' descendants='4.601e-05'/>
      <depth2 name='180' value='0.0' descendants='5.885e-05'/>
    </depth1>
    <depth1 name='129' value='0.0045171' descendants='0.0031624'>
      <depth2 name='126' value='0.00013861' descendants='0.00014924'/>
      <depth2 name='127' value='4.559e-05' descendants='9.367e-05'/>
      <depth2 name='129' value='0.00032838' descendants='0.0002299'/>
      <depth2 name='75' value='0.0' descendants='6.115e-05'/>
    </depth1>
    <depth1 name='125' value='0.00315559' descendants='0.00279098'>
      <depth2 name='125' value='7.265e-05' descendants='6.426e-05'/>
    </depth1>
    <depth1 name='186' value='0.00165926' descendants='0.00195275'>
      <depth2 name='186' value='4.161e-05' descendants='4.897e-05'/>
      <depth2 name='170' value='0.0' descendants='5.149e-05'/>
      <depth2 name='174' value='0.0' descendants='9.709e-05'>
        <depth3 name='173' value='7.072e-05' descendants='4.87e-05'/>
      </depth2>
    </depth1>
    <depth1 name='128' value='0.00161893' descendants='0.0021964'>
      <depth2 name='126' value='0.00028872' descendants='0.00031087'/>
      <depth2 name='127' value='4.19e-05' descendants='8.608e-05'/>
      <depth2 name='125' value='6.583e-05' descendants='5.822e-05'/>
      <depth2 name='120' value='1.027e-05' descendants='7.02e-05'/>
    </depth1>
    <depth1 name='147' value='0.00164706' descendants='0.00132421'>
      <depth2 name='126' value='5.528e-05' descendants='5.952e-05'/>
    </depth1>
    <depth1 name='171' value='0.00069037' descendants='0.00368026'>
      <depth2 name='173' value='0.00063357' descendants='0.00043632'>
        <depth3 name='173' value='7.037e-05' descendants='4.846e-05'/>
      </depth2>
      <depth2 name='126' value='0.00010307' descendants='0.00011098'/>
      <depth2 name='127' value='5.549e-05' descendants='0.00011401'/>
      <depth2 name='125' value='0.00016774' descendants='0.00014836'/>
      <depth2 name='142' value='6.18e-06' descendants='0.00017173'>
        <depth3 name='127' value='3.298e-05' descendants='6.776e-05'/>
      </depth2>
      <depth2 name='202' value='0.00013678' descendants='0.00011212'/>
      <depth2 name='171' value='3.02e-05' descendants='0.00016097'/>
      <depth2 name='141' value='3.19e-06' descendants='8.116e-05'/>
      <depth2 name='320' value='1.305e-05' descendants='6.387e-05'/>
      <depth2 name='170' value='0.0' descendants='0.00037414'>
        <depth3 name='173' value='8.103e-05' descendants='5.581e-05'/>
        <depth3 name='170' value='0.0' descendants='4.59e-05'/>
      </depth2>
      <depth2 name='172' value='0.0' descendants='0.00031756'/>
      <depth2 name='174' value='0.0' descendants='0.00015216'>
        <depth3 name='173' value='0.00011083' descendants='7.632e-05'/>
        <depth3 name='172' value='0.0' descendants='5.628e-05'/>
      </depth2>
      <depth2 name='192' value='0.0' descendants='0.00024762'/>
      <depth2 name='243' value='0.0' descendants='6.365e-05'/>
    </depth1>
    <depth1 name='320' value='0.00061861' descendants='0.00302653'>
      <depth2 name='126' value='5.333e-05' descendants='5.742e-05'/>
      <depth2 name='147' value='0.00032293' descendants='0.00025963'/>
      <depth2 name='142' value='2.57e-06' descendants='7.13e-05'/>
      <depth2 name='146' value='0.00022055' descendants='0.0002324'/>
      <depth2 name='320' value='1.901e-05' descendants='9.3e-05'/>
      <depth2 name='283' value='5.34e-06' descendants='6.977e-05'/>
      <depth2 name='149' value='2.1e-06' descendants='0.00010435'>
        <depth3 name='127' value='2.641e-05' descendants='5.427e-05'/>
      </depth2>
      <depth2 name='243' value='0.0' descendants='6.853e-05'>
        <depth3 name='125' value='5.263e-05' descendants='4.655e-05'/>
      </depth2>
      <depth2 name='372' value='0.0' descendants='4.805e-05'/>
      <depth2 name='113' value='0.0' descendants='8.463e-05'/>
    </depth1>
    <depth1 name='152' value='0.00060975' descendants='0.00143755'>
      <depth2 name='126' value='0.00024948' descendants='0.00026861'/>
      <depth2 name='127' value='5.527e-05' descendants='0.00011356'/>
      <depth2 name='128' value='0.00016738' descendants='0.00022708'/>
      <depth2 name='152' value='4.169e-05' descendants='9.829e-05'/>
    </depth1>
    <depth1 name='106' value='0.00057587' descendants='0.00112009'>
      <depth2 name='126' value='0.00011222' descendants='0.00012083'/>
      <depth2 name='125' value='0.00021581' descendants='0.00019088'/>
    </depth1>
    <depth1 name='146' value='0.00098755' descendants='0.0010406'>
      <depth2 name='127' value='3.916e-05' descendants='8.045e-05'/>
      <depth2 name='128' value='4.02e-05' descendants='5.454e-05'/>
    </depth1>
    <depth1 name='149' value='0.00047382' descendants='0.02354814'>
      <depth2 name='173' value='0.00012293' descendants='8.466e-05'/>
      <depth2 name='126' value='0.00200837' descendants='0.00216241'>
        <depth3 name='126' value='0.00025278' descendants='0.00027217'/>
        <depth3 name='127' value='2.787e-05' descendants='5.725e-05'/>
        <depth3 name='125' value='5.305e-05' descendants='4.692e-05'/>
      </depth2>
      <depth2 name='127' value='0.00596085' descendants='0.01224683'>
        <depth3 name='126' value='0.00335767' descendants='0.0036152'/>
        <depth3 name='127' value='0.00040516' descendants='0.00083242'/>
        <depth3 name='125' value='0.00043375' descendants='0.00038363'/>
        <depth3 name='123' value='0.00025313' descendants='8.172e-05'/>
        <depth3 name='129' value='9.841e-05' descendants='6.889e-05'/>
        <depth3 name='120' value='5.809e-05' descendants='0.00039692'/>
      </depth2>
      <depth2 name='125' value='0.0006815' descendants='0.00060276'/>
      <depth2 name='129' value='0.00125574' descendants='0.00087914'>
        <depth3 name='129' value='9.129e-05' descendants='6.391e-05'/>
      </depth2>
      <depth2 name='120' value='0.00028295' descendants='0.00193331'>
        <depth3 name='126' value='0.00057563' descendants='0.00061979'/>
        <depth3 name='127' value='5.716e-05' descendants='0.00011744'/>
        <depth3 name='125' value='5.947e-05' descendants='5.26e-05'/>
        <depth3 name='120' value='1.27e-05' descendants='8.677e-05'/>
      </depth2>
      <depth2 name='123' value='0.0003413' descendants='0.00011019'/>
      <depth2 name='105' value='6.461e-05' descendants='0.00012493'/>
      <depth2 name='147' value='0.00038183' descendants='0.00030699'/>
      <depth2 name='128' value='0.00030408' descendants='0.00041255'>
        <depth3 name='126' value='5.423e-05' descendants='5.839e-05'/>
      </depth2>
      <depth2 name='142' value='7.689e-05' descendants='0.00213519'>
        <depth3 name='126' value='0.00030234' descendants='0.00032553'/>
        <depth3 name='127' value='0.00041007' descendants='0.00084251'/>
        <depth3 name='125' value='8.996e-05' descendants='7.957e-05'/>
        <depth3 name='129' value='9.495e-05' descendants='6.647e-05'/>
        <depth3 name='120' value='1.949e-05' descendants='0.00013318'/>
        <depth3 name='142' value='3.13e-06' descendants='8.685e-05'/>
      </depth2>
      <depth2 name='202' value='8.434e-05' descendants='6.914e-05'/>
      <depth2 name='106' value='2.612e-05' descendants='5.079e-05'/>
      <depth2 name='146' value='0.00011096' descendants='0.00011692'/>
      <depth2 name='141' value='2.35e-05' descendants='0.0005977'>
        <depth3 name='126' value='9.949e-05' descendants='0.00010712'/>
        <depth3 name='127' value='4.524e-05' descendants='9.295e-05'/>
        <depth3 name='125' value='0.00018887' descendants='0.00016705'/>
      </depth2>
      <depth2 name='320' value='1.649e-05' descendants='8.068e-05'/>
      <depth2 name='144' value='0.00010472' descendants='0.00012421'>
        <depth3 name='127' value='2.412e-05' descendants='4.956e-05'/>
      </depth2>
      <depth2 name='122' value='3.23e-05' descendants='0.0002613'>
        <depth3 name='126' value='4.732e-05' descendants='5.094e-05'/>
      </depth2>
      <depth2 name='143' value='8.44e-06' descendants='0.00040329'>
        <depth3 name='127' value='0.00011055' descendants='0.00022713'/>
      </depth2>
      <depth2 name='149' value='7.47e-06' descendants='0.00037149'>
        <depth3 name='127' value='9.404e-05' descendants='0.0001932'/>
      </depth2>
      <depth2 name='187' value='5.106e-05' descendants='0.00013652'/>
      <depth2 name='195' value='9.41e-06' descendants='4.946e-05'/>
      <depth2 name='172' value='0.0' descendants='5.241e-05'/>
      <depth2 name='174' value='0.0' descendants='0.00013333'>
        <depth3 name='173' value='9.711e-05' descendants='6.688e-05'/>
        <depth3 name='172' value='0.0' descendants='4.932e-05'/>
      </depth2>
      <depth2 name='243' value='0.0' descendants='8.97e-05'>
        <depth3 name='125' value='6.889e-05' descendants='6.093e-05'/>
      </depth2>
      <depth2 name='136' value='0.0' descendants='4.758e-05'/>
      <depth2 name='137' value='4.8e-07' descendants='5.049e-05'/>
      <depth2 name='107' value='0.0' descendants='0.00020148'>
        <depth3 name='105' value='3.57e-05' descendants='6.904e-05'/>
        <depth3 name='106' value='3.164e-05' descendants='6.154e-05'/>
      </depth2>
      <depth2 name='78' value='0.0' descendants='4.456e-05'/>
      <depth2 name='145' value='0.0' descendants='0.00012569'/>
      <depth2 name='244' value='0.0' descendants='4.617e-05'/>
      <depth2 name='76' value='0.0' descendants='0.00010448'>
        <depth3 name='129' value='6.799e-05' descendants='4.76e-05'/>
      </depth2>
    </depth1>
    <depth1 name='142' value='0.00037722' descendants='0.01047586'>
      <depth2 name='126' value='0.00148339' descendants='0.00159716'>
        <depth3 name='126' value='0.0001867' descendants='0.00020103'/>
      </depth2>
      <depth2 name='127' value='0.00201192' descendants='0.00413357'>
        <depth3 name='126' value='0.00113329' descendants='0.00122021'/>
        <depth3 name='127' value='0.00013675' descendants='0.00028096'/>
        <depth3 name='125' value='0.0001464' descendants='0.00012948'/>
        <depth3 name='120' value='1.961e-05' descendants='0.00013397'/>
      </depth2>
      <depth2 name='125' value='0.00044139' descendants='0.00039039'/>
      <depth2 name='129' value='0.00046585' descendants='0.00032614'/>
      <depth2 name='120' value='9.563e-05' descendants='0.00065342'>
        <depth3 name='126' value='0.00019455' descendants='0.00020947'/>
      </depth2>
      <depth2 name='123' value='0.00017981' descendants='5.805e-05'/>
      <depth2 name='128' value='3.854e-05' descendants='5.229e-05'/>
      <depth2 name='142' value='1.534e-05' descendants='0.00042609'>
        <depth3 name='126' value='6.033e-05' descendants='6.496e-05'/>
        <depth3 name='127' value='8.183e-05' descendants='0.00016813'/>
      </depth2>
      <depth2 name='141' value='3.5e-06' descendants='8.894e-05'/>
      <depth2 name='122' value='6.15e-06' descendants='4.977e-05'/>
      <depth2 name='174' value='0.0' descendants='8.715e-05'>
        <depth3 name='173' value='6.348e-05' descendants='4.372e-05'/>
      </depth2>
      <depth2 name='107' value='0.0' descendants='6.016e-05'/>
      <depth2 name='140' value='0.0' descendants='4.614e-05'/>
    </depth1>
    <depth1 name='195' value='0.00054583' descendants='0.00286837'>
      <depth2 name='173' value='0.00019082' descendants='0.00013141'/>
      <depth2 name='126' value='0.00016489' descendants='0.00017754'/>
      <depth2 name='127' value='7.129e-05' descendants='0.00014648'/>
      <depth2 name='125' value='0.00016892' descendants='0.0001494'/>
      <depth2 name='129' value='9.211e-05' descendants='6.449e-05'/>
      <depth2 name='141' value='1.229e-05' descendants='0.00031252'>
        <depth3 name='126' value='5.202e-05' descendants='5.601e-05'/>
        <depth3 name='127' value='2.366e-05' descendants='4.86e-05'/>
        <depth3 name='125' value='9.876e-05' descendants='8.735e-05'/>
      </depth2>
      <depth2 name='195' value='1.36e-05' descendants='7.146e-05'/>
      <depth2 name='170' value='0.0' descendants='8.062e-05'/>
      <depth2 name='172' value='0.0' descendants='9.443e-05'/>
      <depth2 name='174' value='0.0' descendants='4.773e-05'/>
      <depth2 name='136' value='0.0' descendants='0.0002334'>
        <depth3 name='126' value='7.793e-05' descendants='8.391e-05'/>
        <depth3 name='127' value='2.918e-05' descendants='5.996e-05'/>
      </depth2>
    </depth1>
    <depth1 name='123' value='0.0013745' descendants='0.00044376'/>
    <depth1 name='144' value='0.00055102' descendants='0.00065361'>
      <depth2 name='127' value='0.00012693' descendants='0.00026078'>
        <depth3 name='126' value='7.15e-05' descendants='7.698e-05'/>
      </depth2>
    </depth1>
    <depth1 name='182' value='0.00033373' descendants='0.00181187'>
      <depth2 name='173' value='0.00044943' descendants='0.00030951'/>
      <depth2 name='170' value='0.0' descendants='0.00010058'/>
      <depth2 name='172' value='0.0' descendants='0.00022509'/>
      <depth2 name='174' value='0.0' descendants='0.000239'>
        <depth3 name='173' value='0.00017408' descendants='0.00011988'/>
        <depth3 name='172' value='0.0' descendants='8.84e-05'/>
      </depth2>
      <depth2 name='178' value='0.0' descendants='5.52e-05'/>
      <depth2 name='182' value='1.024e-05' descendants='5.558e-05'/>
    </depth1>
    <depth1 name='319' value='0.00068821' descendants='0.00047125'/>
    <depth1 name='141' value='0.00018521' descendants='0.0047108'>
      <depth2 name='126' value='0.00078413' descendants='0.00084428'>
        <depth3 name='126' value='9.869e-05' descendants='0.00010626'/>
      </depth2>
      <depth2 name='127' value='0.00035658' descendants='0.0007326'>
        <depth3 name='126' value='0.00020086' descendants='0.00021626'/>
        <depth3 name='127' value='2.424e-05' descendants='4.98e-05'/>
      </depth2>
      <depth2 name='125' value='0.00148862' descendants='0.00131662'/>
      <depth2 name='129' value='8.539e-05' descendants='5.978e-05'/>
      <depth2 name='120' value='1.872e-05' descendants='0.00012792'/>
      <depth2 name='123' value='0.0005587' descendants='0.00018038'/>
      <depth2 name='142' value='3.08e-06' descendants='8.545e-05'/>
      <depth2 name='141' value='8.11e-06' descendants='0.00020628'>
        <depth3 name='125' value='6.518e-05' descendants='5.765e-05'/>
      </depth2>
      <depth2 name='122' value='8.08e-06' descendants='6.536e-05'/>
    </depth1>
    <depth1 name='122' value='0.00012709' descendants='0.00102805'>
      <depth2 name='126' value='0.00018615' descendants='0.00020043'/>
      <depth2 name='125' value='0.0001498' descendants='0.00013249'/>
    </depth1>
    <depth1 name='306' value='0.00047605' descendants='0.00041016'/>
    <depth1 name='187' value='0.00028606' descendants='0.0007648'>
      <depth2 name='173' value='0.00010413' descendants='7.171e-05'/>
      <depth2 name='172' value='0.0' descendants='5.225e-05'/>
      <depth2 name='174' value='0.0' descendants='0.00020435'>
        <depth3 name='173' value='0.00014884' descendants='0.0001025'/>
        <depth3 name='172' value='0.0' descendants='7.558e-05'/>
      </depth2>
    </depth1>
    <depth1 name='105' value='0.00020321' descendants='0.00039294'>
      <depth2 name='126' value='4.84e-05' descendants='5.211e-05'/>
      <depth2 name='125' value='8.907e-05' descendants='7.878e-05'/>
    </depth1>
    <depth1 name='286' value='0.00018898' descendants='0.00024424'/>
    <depth1 name='143' value='3.605e-05' descendants='0.00172212'>
      <depth2 name='126' value='0.00014599' descendants='0.00015718'/>
      <depth2 name='127' value='0.00047206' descendants='0.00096986'>
        <depth3 name='126' value='0.0002659' descendants='0.0002863'/>
        <depth3 name='127' value='3.209e-05' descendants='6.592e-05'/>
      </depth2>
      <depth2 name='125' value='0.00010835' descendants='9.583e-05'/>
      <depth2 name='129' value='0.00010808' descendants='7.566e-05'/>
      <depth2 name='120' value='2.173e-05' descendants='0.00014848'>
        <depth3 name='126' value='4.421e-05' descendants='4.76e-05'/>
      </depth2>
      <depth2 name='142' value='2.64e-06' descendants='7.342e-05'/>
    </depth1>
    <depth1 name='245' value='3.228e-05' descendants='0.00208939'>
      <depth2 name='125' value='0.00036703' descendants='0.00032462'/>
      <depth2 name='141' value='2.69e-06' descendants='6.855e-05'/>
      <depth2 name='320' value='9.43e-06' descendants='4.612e-05'/>
      <depth2 name='187' value='1.874e-05' descendants='5.011e-05'/>
      <depth2 name='245' value='4.97e-06' descendants='0.0003218'>
        <depth3 name='125' value='5.653e-05' descendants='5.0e-05'/>
        <depth3 name='245' value='7.7e-07' descendants='4.956e-05'/>
        <depth3 name='243' value='0.0' descendants='0.00010888'/>
      </depth2>
      <depth2 name='243' value='0.0' descendants='0.00070692'>
        <depth3 name='125' value='0.00054289' descendants='0.00048017'/>
      </depth2>
      <depth2 name='246' value='1.08e-06' descendants='6.898e-05'/>
    </depth1>
    <depth1 name='283' value='6.272e-05' descendants='0.0008195'>
      <depth2 name='173' value='7.123e-05' descendants='4.905e-05'/>
      <depth2 name='147' value='0.00011218' descendants='9.019e-05'/>
      <depth2 name='283' value='6.52e-06' descendants='8.521e-05'/>
      <depth2 name='180' value='0.0' descendants='7.252e-05'/>
    </depth1>
    <depth1 name='184' value='0.00014721' descendants='0.00022437'>
      <depth2 name='173' value='0.0001752' descendants='0.00012065'/>
      <depth2 name='172' value='0.0' descendants='8.893e-05'/>
    </depth1>
    <depth1 name='379' value='6.6e-07' descendants='0.00101307'>
      <depth2 name='126' value='0.0001271' descendants='0.00013685'/>
      <depth2 name='115' value='5.86e-05' descendants='0.00012031'>
        <depth3 name='20' value='0.0' descendants='5.071e-05'/>
      </depth2>
    </depth1>
    <depth1 name='232' value='2.03e-06' descendants='0.00049792'>
      <depth2 name='173' value='9.741e-05' descendants='6.709e-05'/>
      <depth2 name='128' value='3.783e-05' descendants='5.133e-05'/>
      <depth2 name='172' value='0.0' descendants='4.935e-05'/>
    </depth1>
    <depth1 name='115' value='7.45e-05' descendants='0.00015296'>
      <depth2 name='20' value='0.0' descendants='6.447e-05'/>
    </depth1>
    <depth1 name='107' value='0.0' descendants='0.00161917'>
      <depth2 name='105' value='0.00028692' descendants='0.00055481'>
        <depth3 name='126' value='6.834e-05' descendants='7.358e-05'/>
        <depth3 name='125' value='0.00012577' descendants='0.00011124'/>
      </depth2>
      <depth2 name='106' value='0.00025426' descendants='0.00049454'>
        <depth3 name='126' value='4.955e-05' descendants='5.335e-05'/>
        <depth3 name='125' value='9.529e-05' descendants='8.428e-05'/>
      </depth2>
    </depth1>
    <depth1 name='108' value='8.9e-07' descendants='0.00041189'>
      <depth2 name='127' value='3.528e-05' descendants='7.248e-05'/>
      <depth2 name='105' value='2.979e-05' descendants='5.76e-05'/>
    </depth1>
    <depth1 name='31' value='0.0' descendants='0.00067192'>
      <depth2 name='20' value='0.0' descendants='0.00012384'/>
      <depth2 name='39' value='0.0' descendants='8.946e-05'/>
      <depth2 name='21' value='0.0' descendants='9.248e-05'/>
      <depth2 name='326' value='0.0' descendants='6.2e-05'/>
    </depth1>
    <depth1 name='409' value='1.141e-05' descendants='0.0003665'>
      <depth2 name='147' value='8.715e-05' descendants='7.007e-05'/>
      <depth2 name='263' value='8.139e-05' descendants='4.853e-05'/>
    </depth1>
    <depth1 name='121' value='2.072e-05' descendants='0.00020137'/>
    <depth1 name='148' value='7.03e-06' descendants='0.00019569'>
      <depth2 name='127' value='4.45e-05' descendants='9.142e-05'/>
    </depth1>
    <depth1 name='138' value='4.643e-05' descendants='0.00011952'/>
    <depth1 name='381' value='2.471e-05' descendants='0.00016231'/>
    <depth1 name='165' value='0.0' descendants='0.00213955'>
      <depth2 name='126' value='0.00021966' descendants='0.00023651'/>
      <depth2 name='127' value='2.632e-05' descendants='5.407e-05'/>
      <depth2 name='125' value='0.00068525' descendants='0.00060607'/>
      <depth2 name='106' value='3.931e-05' descendants='7.646e-05'/>
      <depth2 name='77' value='0.0' descendants='0.00036862'>
        <depth3 name='129' value='0.00022359' descendants='0.00015654'/>
        <depth3 name='75' value='0.0' descendants='0.00011702'/>
      </depth2>
      <depth2 name='137' value='6.8e-07' descendants='7.133e-05'/>
      <depth2 name='165' value='0.0' descendants='0.00020312'>
        <depth3 name='125' value='6.506e-05' descendants='5.754e-05'/>
      </depth2>
    </depth1>
    <depth1 name='137' value='1.71e-06' descendants='0.00017898'>
      <depth2 name='126' value='4.182e-05' descendants='4.503e-05'/>
    </depth1>
    <depth1 name='246' value='2.47e-06' descendants='0.0001583'/>
    <depth1 name='368' value='9.5e-07' descendants='0.00028934'>
      <depth2 name='105' value='2.803e-05' descendants='5.42e-05'/>
    </depth1>
    <depth1 name='169' value='0.0' descendants='0.00081001'>
      <depth2 name='127' value='2.281e-05' descendants='4.686e-05'/>
      <depth2 name='202' value='0.00010919' descendants='8.95e-05'/>
      <depth2 name='136' value='0.0' descendants='0.00011764'/>
      <depth2 name='160' value='1.793e-05' descendants='6.25e-05'/>
      <depth2 name='109' value='0.0' descendants='5.747e-05'/>
    </depth1>
    <depth1 name='170' value='0.0' descendants='0.01089258'>
      <depth2 name='173' value='0.00235914' descendants='0.00162468'>
        <depth3 name='173' value='0.00026202' descendants='0.00018044'/>
        <depth3 name='172' value='0.0' descendants='0.00013303'/>
      </depth2>
      <depth2 name='126' value='0.00043054' descendants='0.00046356'>
        <depth3 name='126' value='5.419e-05' descendants='5.835e-05'/>
      </depth2>
      <depth2 name='127' value='5.078e-05' descendants='0.00010433'/>
      <depth2 name='125' value='0.00096836' descendants='0.00085647'/>
      <depth2 name='142' value='4.07e-06' descendants='0.00011305'>
        <depth3 name='127' value='2.171e-05' descendants='4.461e-05'/>
      </depth2>
      <depth2 name='186' value='5.121e-05' descendants='6.027e-05'/>
      <depth2 name='202' value='0.00036414' descendants='0.00029848'/>
      <depth2 name='171' value='9.525e-05' descendants='0.00050777'>
        <depth3 name='173' value='8.741e-05' descendants='6.02e-05'/>
        <depth3 name='170' value='0.0' descendants='5.162e-05'/>
        <depth3 name='172' value='0.0' descendants='4.381e-05'/>
      </depth2>
      <depth2 name='115' value='2.647e-05' descendants='5.435e-05'/>
      <depth2 name='320' value='6.258e-05' descendants='0.00030617'/>
      <depth2 name='283' value='4.07e-06' descendants='5.322e-05'/>
      <depth2 name='149' value='1.33e-06' descendants='6.594e-05'/>
      <depth2 name='121' value='2.415e-05' descendants='0.00023473'>
        <depth3 name='126' value='4.293e-05' descendants='4.622e-05'/>
        <depth3 name='125' value='5.362e-05' descendants='4.742e-05'/>
      </depth2>
      <depth2 name='245' value='1.12e-06' descendants='7.278e-05'/>
      <depth2 name='195' value='2.065e-05' descendants='0.0001085'/>
      <depth2 name='22' value='0.0' descendants='0.00022855'>
        <depth3 name='126' value='4.402e-05' descendants='4.74e-05'/>
      </depth2>
      <depth2 name='170' value='0.0' descendants='0.00133621'>
        <depth3 name='173' value='0.0002894' descendants='0.0001993'/>
        <depth3 name='126' value='5.282e-05' descendants='5.687e-05'/>
        <depth3 name='125' value='0.00011879' descendants='0.00010506'/>
        <depth3 name='170' value='0.0' descendants='0.00016391'/>
        <depth3 name='172' value='0.0' descendants='0.00014394'/>
        <depth3 name='171' value='1.168e-05' descendants='6.229e-05'/>
        <depth3 name='192' value='0.0' descendants='4.665e-05'/>
      </depth2>
      <depth2 name='172' value='0.0' descendants='0.00117337'>
        <depth3 name='173' value='0.000168' descendants='0.0001157'/>
        <depth3 name='172' value='0.0' descendants='8.53e-05'/>
      </depth2>
      <depth2 name='274' value='3.2e-07' descendants='9.391e-05'>
        <depth3 name='126' value='4.33e-05' descendants='4.662e-05'/>
      </depth2>
      <depth2 name='174' value='0.0' descendants='0.0001762'>
        <depth3 name='173' value='0.00012834' descendants='8.838e-05'/>
        <depth3 name='172' value='0.0' descendants='6.517e-05'/>
      </depth2>
      <depth2 name='192' value='0.0' descendants='0.00038025'/>
      <depth2 name='228' value='0.0' descendants='0.00015176'/>
      <depth2 name='243' value='0.0' descendants='0.00016869'>
        <depth3 name='125' value='0.00012955' descendants='0.00011458'/>
      </depth2>
      <depth2 name='322' value='0.0' descendants='8.571e-05'/>
      <depth2 name='324' value='0.0' descendants='0.00011054'/>
      <depth2 name='31' value='0.0' descendants='7.253e-05'/>
      <depth2 name='39' value='0.0' descendants='8.402e-05'/>
      <depth2 name='178' value='0.0' descendants='0.00011173'/>
      <depth2 name='118' value='5.0e-08' descendants='6.24e-05'/>
      <depth2 name='21' value='0.0' descendants='9.788e-05'/>
      <depth2 name='107' value='0.0' descendants='0.00010993'/>
      <depth2 name='176' value='5.22e-06' descendants='5.295e-05'/>
      <depth2 name='372' value='0.0' descendants='4.843e-05'/>
      <depth2 name='155' value='0.0' descendants='0.00011668'/>
      <depth2 name='379' value='3.0e-08' descendants='4.441e-05'/>
      <depth2 name='32' value='0.0' descendants='9.667e-05'/>
      <depth2 name='164' value='0.0' descendants='4.661e-05'/>
    </depth1>
    <depth1 name='371' value='4.9e-07' descendants='0.00015522'/>
    <depth1 name='215' value='7.973e-05' descendants='7.683e-05'/>
    <depth1 name='118' value='1.2e-07' descendants='0.00015362'>
      <depth2 name='125' value='4.956e-05' descendants='4.384e-05'/>
    </depth1>
    <depth1 name='96' value='4.9e-07' descendants='0.00011415'>
      <depth2 name='127' value='2.877e-05' descendants='5.91e-05'/>
    </depth1>
    <depth1 name='76' value='0.0' descendants='0.00036465'>
      <depth2 name='129' value='0.00023729' descendants='0.00016612'/>
      <depth2 name='75' value='0.0' descendants='6.16e-05'/>
    </depth1>
    <depth1 name='360' value='2.8e-07' descendants='0.00013008'/>
    <depth1 name='358' value='1.0e-07' descendants='0.00010253'/>
    <depth1 name='80' value='0.0' descendants='0.00013662'/>
    <depth1 name='157' value='0.0' descendants='9.288e-05'/>
    <depth1 name='172' value='0.0' descendants='0.04448873'>
      <depth2 name='173' value='0.00636974' descendants='0.00438669'>
        <depth3 name='173' value='0.00070745' descendants='0.0004872'/>
        <depth3 name='172' value='0.0' descendants='0.00035918'/>
      </depth2>
      <depth2 name='125' value='9.361e-05' descendants='8.279e-05'/>
      <depth2 name='172' value='0.0' descendants='0.00323415'>
        <depth3 name='173' value='0.00046305' descendants='0.00031889'/>
        <depth3 name='172' value='0.0' descendants='0.00023511'/>
      </depth2>
      <depth2 name='174' value='0.0' descendants='0.00019997'>
        <depth3 name='173' value='0.00014565' descendants='0.00010031'/>
        <depth3 name='172' value='0.0' descendants='7.396e-05'/>
      </depth2>
    </depth1>
    <depth1 name='176' value='7.99e-06' descendants='8.109e-05'/>
    <depth1 name='380' value='1.93e-06' descendants='8.491e-05'/>
    <depth1 name='77' value='0.0' descendants='8.826e-05'/>
    <depth1 name='174' value='0.0' descendants='0.04688717'>
      <depth2 name='173' value='0.03415097' descendants='0.02351897'>
        <depth3 name='173' value='0.00379294' descendants='0.00261211'/>
        <depth3 name='125' value='5.622e-05' descendants='4.972e-05'/>
        <depth3 name='172' value='0.0' descendants='0.0019257'/>
        <depth3 name='174' value='0.0' descendants='0.00015355'/>
      </depth2>
      <depth2 name='126' value='0.00020007' descendants='0.00021542'/>
      <depth2 name='127' value='3.482e-05' descendants='7.154e-05'/>
      <depth2 name='125' value='0.00022206' descendants='0.0001964'/>
      <depth2 name='142' value='2.43e-06' descendants='6.761e-05'/>
      <depth2 name='320' value='1.005e-05' descendants='4.918e-05'/>
      <depth2 name='195' value='1.081e-05' descendants='5.682e-05'/>
      <depth2 name='172' value='0.0' descendants='0.01734246'>
        <depth3 name='173' value='0.00248303' descendants='0.00171001'/>
        <depth3 name='172' value='0.0' descendants='0.00126073'/>
        <depth3 name='174' value='0.0' descendants='7.795e-05'/>
      </depth2>
      <depth2 name='174' value='0.0' descendants='0.00689276'>
        <depth3 name='173' value='0.00502044' descendants='0.00345746'/>
        <depth3 name='172' value='0.0' descendants='0.00254947'/>
        <depth3 name='174' value='0.0' descendants='0.00101329'/>
        <depth3 name='243' value='0.0' descendants='4.603e-05'/>
      </depth2>
      <depth2 name='243' value='0.0' descendants='0.00031311'>
        <depth3 name='125' value='0.00024046' descendants='0.00021267'/>
      </depth2>
      <depth2 name='193' value='0.0' descendants='8.657e-05'/>
    </depth1>
    <depth1 name='177' value='0.0' descendants='0.0003797'>
      <depth2 name='126' value='5.706e-05' descendants='6.144e-05'/>
      <depth2 name='177' value='0.0' descendants='8.62e-05'/>
    </depth1>
    <depth1 name='178' value='0.0' descendants='0.00106502'>
      <depth2 name='173' value='0.00029401' descendants='0.00020248'/>
      <depth2 name='126' value='6.704e-05' descendants='7.219e-05'/>
      <depth2 name='125' value='4.951e-05' descendants='4.379e-05'/>
      <depth2 name='172' value='0.0' descendants='0.00014925'/>
      <depth2 name='174' value='0.0' descendants='6.13e-05'/>
      <depth2 name='178' value='0.0' descendants='5.654e-05'/>
    </depth1>
    <depth1 name='179' value='0.0' descendants='0.00205996'>
      <depth2 name='173' value='0.00046379' descendants='0.0003194'/>
      <depth2 name='202' value='0.00021505' descendants='0.00017627'/>
      <depth2 name='171' value='9.73e-06' descendants='5.186e-05'/>
      <depth2 name='320' value='1.184e-05' descendants='5.795e-05'/>
      <depth2 name='195' value='9.25e-06' descendants='4.86e-05'/>
      <depth2 name='170' value='0.0' descendants='0.0001531'/>
      <depth2 name='172' value='0.0' descendants='0.00023142'/>
      <depth2 name='193' value='0.0' descendants='4.685e-05'/>
      <depth2 name='178' value='0.0' descendants='4.483e-05'/>
    </depth1>
    <depth1 name='85' value='0.0' descendants='0.00010197'>
      <depth2 name='129' value='6.915e-05' descendants='4.841e-05'/>
    </depth1>
    <depth1 name='180' value='0.0' descendants='0.02039233'>
      <depth2 name='173' value='0.01541455' descendants='0.01061564'>
        <depth3 name='173' value='0.001712' descendants='0.00117902'/>
        <depth3 name='172' value='0.0' descendants='0.00086919'/>
        <depth3 name='174' value='0.0' descendants='6.931e-05'/>
      </depth2>
      <depth2 name='126' value='0.00010333' descendants='0.00011125'/>
      <depth2 name='125' value='0.00014714' descendants='0.00013014'/>
      <depth2 name='202' value='0.0001649' descendants='0.00013517'/>
      <depth2 name='152' value='2.452e-05' descendants='5.781e-05'/>
      <depth2 name='172' value='0.0' descendants='0.00783839'>
        <depth3 name='173' value='0.00112227' descendants='0.00077288'/>
        <depth3 name='172' value='0.0' descendants='0.00056982'/>
      </depth2>
      <depth2 name='174' value='0.0' descendants='0.00024885'>
        <depth3 name='173' value='0.00018126' descendants='0.00012483'/>
        <depth3 name='172' value='0.0' descendants='9.204e-05'/>
      </depth2>
      <depth2 name='177' value='0.0' descendants='7.444e-05'/>
      <depth2 name='178' value='0.0' descendants='8.165e-05'/>
      <depth2 name='209' value='0.0' descendants='4.517e-05'/>
    </depth1>
    <depth1 name='376' value='4.38e-06' descendants='6.854e-05'/>
    <depth1 name='181' value='0.0' descendants='0.000889'>
      <depth2 name='173' value='0.00037721' descendants='0.00025978'/>
      <depth2 name='170' value='0.0' descendants='6.648e-05'/>
      <depth2 name='172' value='0.0' descendants='0.00019094'/>
      <depth2 name='174' value='0.0' descendants='0.00017792'>
        <depth3 name='173' value='0.00012959' descendants='8.925e-05'/>
        <depth3 name='172' value='0.0' descendants='6.581e-05'/>
      </depth2>
    </depth1>
    <depth1 name='307' value='1.71e-06' descendants='6.67e-05'/>
    <depth1 name='113' value='0.0' descendants='0.00031894'>
      <depth2 name='105' value='5.358e-05' descendants='0.0001036'/>
    </depth1>
    <depth1 name='183' value='0.0' descendants='0.00073448'>
      <depth2 name='173' value='9.024e-05' descendants='6.215e-05'/>
      <depth2 name='172' value='0.0' descendants='4.527e-05'/>
      <depth2 name='174' value='0.0' descendants='0.000115'>
        <depth3 name='173' value='8.376e-05' descendants='5.769e-05'/>
      </depth2>
    </depth1>
    <depth1 name='185' value='0.0' descendants='0.00028739'>
      <depth2 name='173' value='0.00011467' descendants='7.897e-05'/>
      <depth2 name='172' value='0.0' descendants='5.824e-05'/>
    </depth1>
    <depth1 name='188' value='0.0' descendants='7.142e-05'/>
    <depth1 name='190' value='0.0' descendants='0.00283'>
      <depth2 name='173' value='0.00089381' descendants='0.00061555'>
        <depth3 name='173' value='9.927e-05' descendants='6.837e-05'/>
        <depth3 name='172' value='0.0' descendants='5.04e-05'/>
      </depth2>
      <depth2 name='172' value='0.0' descendants='0.00045098'>
        <depth3 name='173' value='6.457e-05' descendants='4.447e-05'/>
      </depth2>
      <depth2 name='174' value='0.0' descendants='0.00099748'>
        <depth3 name='173' value='0.00072653' descendants='0.00050035'/>
        <depth3 name='172' value='0.0' descendants='0.00036895'/>
        <depth3 name='174' value='0.0' descendants='0.00014664'/>
      </depth2>
      <depth2 name='136' value='0.0' descendants='4.811e-05'/>
      <depth2 name='190' value='0.0' descendants='0.00034271'>
        <depth3 name='173' value='0.00010824' descendants='7.454e-05'/>
        <depth3 name='172' value='0.0' descendants='5.461e-05'/>
        <depth3 name='174' value='0.0' descendants='0.00012079'/>
      </depth2>
    </depth1>
    <depth1 name='119' value='0.0' descendants='0.00022259'>
      <depth2 name='126' value='6.913e-05' descendants='7.443e-05'/>
    </depth1>
    <depth1 name='191' value='0.0' descendants='0.00018149'/>
    <depth1 name='192' value='0.0' descendants='0.00019813'/>
    <depth1 name='193' value='0.0' descendants='0.00429413'>
      <depth2 name='173' value='0.0004779' descendants='0.00032912'/>
      <depth2 name='186' value='0.00032386' descendants='0.00038114'/>
      <depth2 name='202' value='0.00011786' descendants='9.66e-05'/>
      <depth2 name='141' value='3.06e-06' descendants='7.78e-05'/>
      <depth2 name='170' value='0.0' descendants='6.435e-05'/>
      <depth2 name='172' value='0.0' descendants='0.00024034'/>
      <depth2 name='174' value='0.0' descendants='0.00074329'>
        <depth3 name='173' value='0.00054139' descendants='0.00037284'/>
        <depth3 name='172' value='0.0' descendants='0.00027492'/>
        <depth3 name='174' value='0.0' descendants='0.00010927'/>
      </depth2>
      <depth2 name='243' value='0.0' descendants='4.491e-05'/>
      <depth2 name='136' value='0.0' descendants='0.00013182'>
        <depth3 name='126' value='4.401e-05' descendants='4.739e-05'/>
      </depth2>
      <depth2 name='193' value='0.0' descendants='0.00013991'/>
      <depth2 name='180' value='0.0' descendants='0.00057604'>
        <depth3 name='173' value='0.00043543' descendants='0.00029987'/>
        <depth3 name='172' value='0.0' descendants='0.00022142'/>
      </depth2>
    </depth1>
    <depth1 name='309' value='5.771e-05' descendants='4.725e-05'/>
    <depth1 name='194' value='0.0' descendants='0.00197992'>
      <depth2 name='173' value='6.936e-05' descendants='4.777e-05'/>
      <depth2 name='202' value='9.402e-05' descendants='7.707e-05'/>
      <depth2 name='171' value='1.127e-05' descendants='6.007e-05'/>
      <depth2 name='170' value='0.0' descendants='0.00014645'/>
      <depth2 name='174' value='0.0' descendants='0.00036217'>
        <depth3 name='173' value='0.00026379' descendants='0.00018167'/>
        <depth3 name='172' value='0.0' descendants='0.00013396'/>
        <depth3 name='174' value='0.0' descendants='5.324e-05'/>
      </depth2>
      <depth2 name='192' value='0.0' descendants='7.647e-05'/>
      <depth2 name='243' value='0.0' descendants='5.631e-05'/>
      <depth2 name='177' value='0.0' descendants='4.766e-05'/>
      <depth2 name='180' value='0.0' descendants='0.00022151'>
        <depth3 name='173' value='0.00016744' descendants='0.00011531'/>
        <depth3 name='172' value='0.0' descendants='8.514e-05'/>
      </depth2>
      <depth2 name='191' value='0.0' descendants='7.924e-05'/>
      <depth2 name='217' value='0.0' descendants='5.326e-05'/>
    </depth1>
    <depth1 name='361' value='9.6e-07' descendants='5.728e-05'/>
    <depth1 name='32' value='0.0' descendants='0.00030512'>
      <depth2 name='20' value='0.0' descendants='0.00012092'/>
      <depth2 name='326' value='0.0' descendants='6.04e-05'/>
    </depth1>
    <depth1 name='197' value='0.0' descendants='0.00098478'>
      <depth2 name='173' value='0.00030723' descendants='0.00021158'/>
      <depth2 name='172' value='0.0' descendants='0.00015552'/>
      <depth2 name='180' value='0.0' descendants='0.00017347'>
        <depth3 name='173' value='0.00013113' descendants='9.03e-05'/>
        <depth3 name='172' value='0.0' descendants='6.668e-05'/>
      </depth2>
    </depth1>
    <depth1 name='198' value='0.0' descendants='0.00013537'/>
    <depth1 name='39' value='0.0' descendants='0.00185564'>
      <depth2 name='173' value='0.00012416' descendants='8.551e-05'/>
      <depth2 name='147' value='0.00018589' descendants='0.00014945'/>
      <depth2 name='186' value='4.091e-05' descendants='4.815e-05'/>
      <depth2 name='146' value='9.691e-05' descendants='0.00010212'/>
      <depth2 name='144' value='4.87e-05' descendants='5.777e-05'/>
      <depth2 name='149' value='2.07e-06' descendants='0.00010263'>
        <depth3 name='127' value='2.598e-05' descendants='5.338e-05'/>
      </depth2>
      <depth2 name='187' value='2.319e-05' descendants='6.201e-05'/>
      <depth2 name='215' value='6.977e-05' descendants='6.723e-05'/>
      <depth2 name='172' value='0.0' descendants='5.865e-05'/>
      <depth2 name='136' value='0.0' descendants='4.946e-05'/>
    </depth1>
    <depth1 name='27' value='0.0' descendants='6.563e-05'/>
    <depth1 name='249' value='7.04e-06' descendants='4.985e-05'/>
    <depth1 name='207' value='0.0' descendants='0.00012216'/>
    <depth1 name='209' value='0.0' descendants='0.00045278'/>
    <depth1 name='99' value='8.0e-08' descendants='5.158e-05'/>
    <depth1 name='217' value='0.0' descendants='0.00357514'>
      <depth2 name='173' value='0.00072254' descendants='0.0004976'>
        <depth3 name='173' value='8.025e-05' descendants='5.527e-05'/>
      </depth2>
      <depth2 name='126' value='7.725e-05' descendants='8.318e-05'/>
      <depth2 name='127' value='0.0001863' descendants='0.00038276'>
        <depth3 name='126' value='0.00010494' descendants='0.00011299'/>
      </depth2>
      <depth2 name='120' value='8.71e-06' descendants='5.953e-05'/>
      <depth2 name='142' value='3.1e-06' descendants='8.596e-05'/>
      <depth2 name='202' value='5.727e-05' descendants='4.694e-05'/>
      <depth2 name='149' value='3.89e-06' descendants='0.00019322'>
        <depth3 name='127' value='4.891e-05' descendants='0.00010049'/>
      </depth2>
      <depth2 name='170' value='0.0' descendants='8.938e-05'/>
      <depth2 name='172' value='0.0' descendants='0.00036505'/>
      <depth2 name='174' value='0.0' descendants='0.00038473'>
        <depth3 name='173' value='0.00028022' descendants='0.00019298'/>
        <depth3 name='172' value='0.0' descendants='0.0001423'/>
        <depth3 name='174' value='0.0' descendants='5.656e-05'/>
      </depth2>
      <depth2 name='180' value='0.0' descendants='0.00016733'>
        <depth3 name='173' value='0.00012648' descendants='8.711e-05'/>
        <depth3 name='172' value='0.0' descendants='6.432e-05'/>
      </depth2>
    </depth1>
    <depth1 name='78' value='0.0' descendants='0.00017099'>
      <depth2 name='129' value='7.194e-05' descendants='5.037e-05'/>
    </depth1>
    <depth1 name='163' value='0.0' descendants='6.021e-05'/>
    <depth1 name='159' value='0.0' descendants='0.00011747'/>
    <depth1 name='218' value='0.0' descendants='0.00223332'>
      <depth2 name='173' value='0.00013732' descendants='9.457e-05'/>
      <depth2 name='127' value='2.647e-05' descendants='5.439e-05'/>
      <depth2 name='147' value='5.638e-05' descendants='4.533e-05'/>
      <depth2 name='142' value='1.72e-06' descendants='4.767e-05'/>
      <depth2 name='202' value='7.109e-05' descendants='5.827e-05'/>
      <depth2 name='283' value='4.42e-06' descendants='5.776e-05'/>
      <depth2 name='170' value='0.0' descendants='0.00012307'/>
      <depth2 name='172' value='0.0' descendants='6.882e-05'/>
      <depth2 name='174' value='0.0' descendants='0.00025099'>
        <depth3 name='173' value='0.00018281' descendants='0.0001259'/>
        <depth3 name='172' value='0.0' descendants='9.284e-05'/>
      </depth2>
      <depth2 name='243' value='0.0' descendants='5.139e-05'/>
      <depth2 name='193' value='0.0' descendants='4.442e-05'/>
      <depth2 name='180' value='0.0' descendants='0.00012256'>
        <depth3 name='173' value='9.264e-05' descendants='6.38e-05'/>
        <depth3 name='172' value='0.0' descendants='4.711e-05'/>
      </depth2>
      <depth2 name='218' value='0.0' descendants='4.577e-05'/>
    </depth1>
    <depth1 name='236' value='5.0e-07' descendants='4.786e-05'/>
    <depth1 name='219' value='0.0' descendants='0.00102041'>
      <depth2 name='170' value='0.0' descendants='5.306e-05'/>
      <depth2 name='174' value='0.0' descendants='0.0001146'>
        <depth3 name='173' value='8.347e-05' descendants='5.748e-05'/>
      </depth2>
      <depth2 name='178' value='0.0' descendants='9.708e-05'/>
    </depth1>
    <depth1 name='220' value='0.0' descendants='0.00013222'/>
    <depth1 name='227' value='0.0' descendants='6.24e-05'/>
    <depth1 name='145' value='0.0' descendants='0.00048305'>
      <depth2 name='126' value='9.539e-05' descendants='0.00010271'/>
      <depth2 name='127' value='6.551e-05' descendants='0.00013459'/>
      <depth2 name='125' value='0.00010548' descendants='9.329e-05'/>
      <depth2 name='142' value='2.67e-06' descendants='7.419e-05'/>
    </depth1>
    <depth1 name='233' value='0.0' descendants='0.00037678'>
      <depth2 name='174' value='0.0' descendants='6.067e-05'/>
      <depth2 name='180' value='0.0' descendants='5.623e-05'/>
    </depth1>
    <depth1 name='242' value='0.0' descendants='0.00032395'>
      <depth2 name='125' value='5.066e-05' descendants='4.48e-05'/>
    </depth1>
    <depth1 name='243' value='0.0' descendants='0.00477723'>
      <depth2 name='173' value='0.00016997' descendants='0.00011706'/>
      <depth2 name='126' value='0.00011239' descendants='0.00012101'/>
      <depth2 name='125' value='0.00366879' descendants='0.00324488'>
        <depth3 name='125' value='8.447e-05' descendants='7.471e-05'/>
      </depth2>
      <depth2 name='142' value='2.09e-06' descendants='5.796e-05'/>
      <depth2 name='141' value='2.87e-06' descendants='7.288e-05'/>
      <depth2 name='121' value='4.72e-06' descendants='4.591e-05'/>
      <depth2 name='243' value='0.0' descendants='0.0001946'>
        <depth3 name='125' value='0.00014945' descendants='0.00013218'/>
      </depth2>
    </depth1>
    <depth1 name='212' value='0.0' descendants='4.564e-05'/>
    <depth1 name='244' value='0.0' descendants='0.00017308'/>
    <depth1 name='251' value='0.0' descendants='6.837e-05'/>
    <depth1 name='260' value='0.0' descendants='6.407e-05'/>
    <depth1 name='266' value='0.0' descendants='0.00057461'>
      <depth2 name='170' value='0.0' descendants='4.498e-05'/>
      <depth2 name='174' value='0.0' descendants='0.00012384'>
        <depth3 name='173' value='9.02e-05' descendants='6.212e-05'/>
        <depth3 name='172' value='0.0' descendants='4.581e-05'/>
      </depth2>
      <depth2 name='177' value='0.0' descendants='5.325e-05'/>
    </depth1>
    <depth1 name='267' value='0.0' descendants='0.00011207'/>
    <depth1 name='269' value='0.0' descendants='0.00019795'/>
    <depth1 name='272' value='0.0' descendants='0.00017243'>
      <depth2 name='127' value='2.883e-05' descendants='5.924e-05'/>
    </depth1>
    <depth1 name='273' value='0.0' descendants='5.763e-05'/>
    <depth1 name='275' value='0.0' descendants='6.785e-05'/>
    <depth1 name='285' value='0.0' descendants='0.00052377'>
      <depth2 name='286' value='4.775e-05' descendants='6.171e-05'/>
      <depth2 name='285' value='0.0' descendants='0.00013127'/>
    </depth1>
    <depth1 name='315' value='0.0' descendants='6.355e-05'/>
    <depth1 name='316' value='0.0' descendants='0.00011282'/>
    <depth1 name='100' value='0.0' descendants='7.353e-05'/>
    <depth1 name='321' value='0.0' descendants='0.00010272'/>
    <depth1 name='322' value='0.0' descendants='0.00016107'/>
    <depth1 name='324' value='0.0' descendants='0.00076672'>
      <depth2 name='115' value='3.863e-05' descendants='7.93e-05'/>
      <depth2 name='283' value='9.59e-06' descendants='0.00012537'/>
    </depth1>
    <depth1 name='325' value='0.0' descendants='0.00011196'/>
    <depth1 name='327' value='0.0' descendants='5.543e-05'/>
    <depth1 name='330' value='0.0' descendants='0.0002871'/>
    <depth1 name='332' value='0.0' descendants='0.0001473'>
      <depth2 name='105' value='3.641e-05' descendants='7.04e-05'/>
    </depth1>
    <depth1 name='333' value='0.0' descendants='8.441e-05'/>
    <depth1 name='339' value='0.0' descendants='7.711e-05'/>
    <depth1 name='342' value='0.0' descendants='0.00032662'>
      <depth2 name='342' value='0.0' descendants='4.951e-05'/>
    </depth1>
    <depth1 name='344' value='0.0' descendants='0.00020127'/>
    <depth1 name='346' value='0.0' descendants='0.00010615'/>
    <depth1 name='347' value='0.0' descendants='0.00015766'/>
    <depth1 name='351' value='0.0' descendants='0.00013253'/>
    <depth1 name='352' value='0.0' descendants='0.00044251'/>
    <depth1 name='353' value='0.0' descendants='0.00011926'/>
    <depth1 name='355' value='0.0' descendants='0.00022827'/>
    <depth1 name='357' value='0.0' descendants='0.00014584'/>
    <depth1 name='359' value='0.0' descendants='0.00013493'/>
    <depth1 name='362' value='0.0' descendants='0.00025805'>
      <depth2 name='342' value='0.0' descendants='4.521e-05'/>
    </depth1>
    <depth1 name='363' value='0.0' descendants='9.757e-05'/>
    <depth1 name='365' value='0.0' descendants='9.085e-05'/>
    <depth1 name='367' value='0.0' descendants='0.00055603'>
      <depth2 name='126' value='5.428e-05' descendants='5.845e-05'/>
    </depth1>
    <depth1 name='372' value='0.0' descendants='0.00218422'>
      <depth2 name='202' value='6.73e-05' descendants='5.516e-05'/>
      <depth2 name='283' value='3.34e-06' descendants='4.364e-05'/>
      <depth2 name='138' value='5.23e-05' descendants='0.00013463'/>
      <depth2 name='368' value='4.9e-07' descendants='0.00014953'/>
      <depth2 name='113' value='0.0' descendants='0.00019677'>
        <depth3 name='105' value='3.305e-05' descendants='6.392e-05'/>
      </depth2>
      <depth2 name='342' value='0.0' descendants='8.059e-05'/>
      <depth2 name='332' value='0.0' descendants='7.675e-05'/>
      <depth2 name='365' value='0.0' descendants='4.529e-05'/>
      <depth2 name='404' value='0.0' descendants='7.093e-05'/>
    </depth1>
    <depth1 name='221' value='0.0' descendants='4.694e-05'/>
    <depth1 name='151' value='0.0' descendants='6.356e-05'/>
    <depth1 name='136' value='0.0' descendants='0.00063508'>
      <depth2 name='126' value='0.00021204' descendants='0.0002283'/>
      <depth2 name='127' value='7.94e-05' descendants='0.00016314'>
        <depth3 name='126' value='4.473e-05' descendants='4.816e-05'/>
      </depth2>
      <depth2 name='122' value='9.61e-06' descendants='7.775e-05'/>
    </depth1>
    <depth1 name='196' value='0.0' descendants='4.538e-05'/>
    <depth1 name='402' value='0.0' descendants='0.00014182'/>
    <depth1 name='404' value='0.0' descendants='0.0005889'>
      <depth2 name='147' value='8.727e-05' descendants='7.017e-05'/>
      <depth2 name='146' value='8.303e-05' descendants='8.749e-05'/>
    </depth1>
    <depth1 name='406' value='0.0' descendants='0.00086601'>
      <depth2 name='283' value='3.063e-05' descendants='0.00040029'>
        <depth3 name='147' value='5.48e-05' descendants='4.405e-05'/>
      </depth2>
      <depth2 name='149' value='1.65e-06' descendants='8.215e-05'/>
    </depth1>
    <depth1 name='407' value='0.0' descendants='0.00015764'/>
    <depth1 name='408' value='0.0' descendants='0.00063523'>
      <depth2 name='126' value='8.882e-05' descendants='9.563e-05'/>
    </depth1>
    <depth1 name='109' value='0.0' descendants='0.00013526'/>
    <depth1 name='416' value='0.0' descendants='6.567e-05'/>
    <depth1 name='420' value='0.0' descendants='0.00023858'/>
  </depth0>
</top>